README.md
setup.py
nameko_mongoengine/__init__.py
nameko_mongoengine/constants.py
nameko_mongoengine/database.py
nameko_mongoengine/mongo_engine.py
nameko_mongoengine/version.py
nameko_mongoengine.egg-info/PKG-INFO
nameko_mongoengine.egg-info/SOURCES.txt
nameko_mongoengine.egg-info/dependency_links.txt
nameko_mongoengine.egg-info/requires.txt
nameko_mongoengine.egg-info/top_level.txt