Metadata-Version: 2.1
Name: nameko-mongoengine
Version: 0.1.0
Summary: Mongoengine dependency provider for Nameko microservice framework
Home-page: https://github.com/ketgo/nameko-mongoengine
Author: Ketan Goyal
Author-email: ketangoyal1988@gmail.com
License: Apache 2.0 license
Keywords: nameko,mongoengine,mongodb,database,nosql,gridfs
Platform: UNKNOWN
Classifier: Intended Audience :: Developers
Classifier: License :: OSI Approved :: Apache Software License
Classifier: Operating System :: OS Independent
Classifier: Topic :: Internet
Classifier: Topic :: Software Development :: Libraries :: Python Modules
Classifier: Natural Language :: English
Classifier: Programming Language :: Python
Classifier: Programming Language :: Python :: 3.5
Classifier: Programming Language :: Python :: 3.6
Classifier: Programming Language :: Python :: 3.7
Requires-Python: >=3.4
Provides-Extra: dev
